thrivve_core/__init__.py
thrivve_core/base.py
thrivve_core/app_decorators/__init__.py
thrivve_core/app_decorators/app_entry.py
thrivve_core/app_decorators/handle_auth.py
thrivve_core/app_decorators/handle_exceptions.py
thrivve_core/app_decorators/handle_response.py
thrivve_core/app_decorators/serializer.py
thrivve_core/helpers/__init__.py
thrivve_core/helpers/acl_enum.py
thrivve_core/helpers/atomic_transactions.py
thrivve_core/helpers/atomic_transactions_v2.py
thrivve_core/helpers/auth.py
thrivve_core/helpers/config.py
thrivve_core/helpers/enums.py
thrivve_core/helpers/exceptions.py
thrivve_core/helpers/fetch_relational_data.py
thrivve_core/helpers/filters.py
thrivve_core/helpers/format_exception.py
thrivve_core/helpers/get_callback.py
thrivve_core/helpers/get_country_code.py
thrivve_core/helpers/get_embedded_function.py
thrivve_core/helpers/get_obj_value.py
thrivve_core/helpers/get_prefix.py
thrivve_core/helpers/kafka_listener.py
thrivve_core/helpers/kafka_producer.py
thrivve_core/helpers/log_config.py
thrivve_core/helpers/micro_fetcher.py
thrivve_core/helpers/numbers.py
thrivve_core/helpers/search_function.py
thrivve_core/helpers/service_config.py
thrivve_core/helpers/sql.py
thrivve_core/helpers/system_roles.py
thrivve_core/helpers/time.py
thrivve_core/helpers/topics.py
thrivve_core/helpers/validate_mobile_number.py
thrivve_core/helpers/validate_parameters.py
thrivve_core/helpers/amazon/__init__.py
thrivve_core/helpers/amazon/append_plain_urls_to_list_dict.py
thrivve_core/helpers/amazon/get_file_url.py
thrivve_core/helpers/amazon/get_plain_url.py
thrivve_core/helpers/amazon/get_s3_client.py
thrivve_core/helpers/amazon/upload_file.py
thrivve_core/helpers/database/__init__.py
thrivve_core/helpers/database/base_model.py
thrivve_core/helpers/database/log_model.py
thrivve_core/helpers/kafka_producers/__init__.py
thrivve_core/helpers/kafka_producers/log_model_changes.py
thrivve_core/helpers/kafka_producers/notification_center.py
thrivve_core-0.3.2.dist-info/METADATA
thrivve_core-0.3.2.dist-info/WHEEL
thrivve_core-0.3.2.dist-info/top_level.txt
thrivve_core-0.3.2.dist-info/RECORD
