Metadata-Version: 2.1
Name: thrivve-core
Version: 0.3.2
Summary: thrivveCore package
Home-page: https://www.wedeliverapp.com/
Author: Eyad Farra
Author-email: info@wedeliverapp.com
License: MIT
Classifier: Development Status :: 4 - Beta
Classifier: Intended Audience :: Developers
Classifier: Topic :: Internet
Classifier: License :: OSI Approved :: MIT License
Classifier: Programming Language :: Python
Classifier: Programming Language :: Python :: 3
Classifier: Programming Language :: Python :: 3.3
Classifier: Programming Language :: Python :: 3.4
Classifier: Programming Language :: Python :: 3.5
Classifier: Programming Language :: Python :: 3.6
Requires-Dist: SQLAlchemy
Requires-Dist: Flask-SQLAlchemy
Requires-Dist: flask-marshmallow
Requires-Dist: confluent-kafka
Requires-Dist: requests
Requires-Dist: python-dotenv
